{
  "gitSyncId": "665ff03890031b34850fab0e_24f49ee3-004a-4375-b3ee-bd342089aa0d",
  "id": "Edit Products_Dynamic_Video.hideInput2",
  "pluginId": "js-plugin",
  "pluginType": "JS",
  "unpublishedAction": {
    "actionConfiguration": {
      "encodeParamsToggle": true,
      "jsArguments": [],
      "paginationType": "NONE",
      "timeoutInMillisecond": 10000
    },
    "collectionId": "Edit Products_Dynamic_Video",
    "confirmBeforeExecute": false,
    "datasource": {
      "isAutoGenerated": false,
      "name": "UNUSED_DATASOURCE",
      "pluginId": "js-plugin"
    },
    "dynamicBindingPathList": [
      {
        "key": "body"
      }
    ],
    "executeOnLoad": false,
    "fullyQualifiedName": "Dynamic_Video.hideInput2",
    "name": "hideInput2",
    "pageId": "Edit Products",
    "userSetOnLoad": false
  }
}