{
  "animateLoading": true,
  "borderRadius": "{{appsmith.theme.borderRadius.appBorderRadius}}",
  "bottomRow": 71,
  "displayName": "Text",
  "dynamicBindingPathList": [
    {
      "key": "truncateButtonColor"
    },
    {
      "key": "fontFamily"
    },
    {
      "key": "borderRadius"
    }
  ],
  "dynamicHeight": "AUTO_HEIGHT",
  "dynamicTriggerPathList": [],
  "fontFamily": "{{appsmith.theme.fontFamily.appFont}}",
  "fontSize": "0.875rem",
  "fontStyle": "",
  "hideCard": false,
  "iconSVG": "/static/media/icon.a55b701a2ae86aa2c6718ecb7b4083f0.svg",
  "isDeprecated": false,
  "isLoading": false,
  "isVisible": true,
  "key": "qsre5249cq",
  "leftColumn": 0,
  "maxDynamicHeight": 9000,
  "minDynamicHeight": 4,
  "minWidth": 450,
  "mobileBottomRow": 66,
  "mobileLeftColumn": 0,
  "mobileRightColumn": 16,
  "mobileTopRow": 62,
  "needsErrorInfo": false,
  "onCanvasUI": {
    "disableParentSelection": false,
    "focusBGCSSVar": "--on-canvas-ui-widget-focus",
    "focusColorCSSVar": "--on-canvas-ui-widget-selection",
    "selectionBGCSSVar": "--on-canvas-ui-widget-selection",
    "selectionColorCSSVar": "--on-canvas-ui-widget-focus"
  },
  "originalBottomRow": 64,
  "originalTopRow": 60,
  "overflow": "NONE",
  "parentColumnSpace": 12.661735534667969,
  "parentId": "9jmuxc72ia",
  "parentRowSpace": 10,
  "renderMode": "CANVAS",
  "responsiveBehavior": "fill",
  "rightColumn": 16,
  "searchTags": [
    "typography",
    "paragraph",
    "label"
  ],
  "shouldTruncate": false,
  "tags": [
    "Suggested",
    "Content"
  ],
  "text": "Image",
  "textAlign": "LEFT",
  "textColor": "#231F20",
  "thumbnailSVG": "https://appcdn.appsmith.com/static/media/thumbnail.0c129b82c9b3e4cd4920563b289659ab.svg",
  "topRow": 67,
  "truncateButtonColor": "{{appsmith.theme.colors.primaryColor}}",
  "type": "TEXT_WIDGET",
  "version": 1,
  "widgetId": "kimwos0ng5",
  "widgetName": "Text2"
}