{
    "boxShadow": "none",
    "iconSVG": "/static/media/icon.a62f1265827a5af78966a733a05697db.svg",
    "labelText": "Labour Group",
    "topRow": 197,
    "labelWidth": 5,
    "type": "SELECT_WIDGET",
    "serverSideFiltering": true,
    "defaultOptionValue": "",
    "animateLoading": true,
    "leftColumn": 0,
    "dynamicBindingPathList": [
        {"key": "accentColor"},
        {"key": "borderRadius"},
        {"key": "sourceData"}
    ],
    "placeholderText": "--Select Labour Group--",
    "isDisabled": false,
    "isRequired": false,
    "dynamicHeight": "FIXED",
    "accentColor": "{{appsmith.theme.colors.primaryColor}}",
    "onCanvasUI": {
        "focusBGCSSVar": "--on-canvas-ui-widget-focus",
        "disableParentSelection": false,
        "focusColorCSSVar": "--on-canvas-ui-widget-selection",
        "selectionBGCSSVar": "--on-canvas-ui-widget-selection",
        "selectionColorCSSVar": "--on-canvas-ui-widget-focus"
    },
    "isVisible": true,
    "version": 1,
    "tags": [
        "Suggested",
        "Select"
    ],
    "isLoading": false,
    "borderRadius": "{{appsmith.theme.borderRadius.appBorderRadius}}",
    "originalBottomRow": 204,
    "needsErrorInfo": false,
    "mobileBottomRow": 218,
    "widgetName": "Select9Copy",
    "isFilterable": false,
    "dynamicPropertyPathList": [{"key": "sourceData"}],
    "displayName": "Select",
    "searchTags": ["dropdown"],
    "bottomRow": 204,
    "parentRowSpace": 10,
    "hideCard": false,
    "mobileRightColumn": 7,
    "parentColumnSpace": 13.71875,
    "dynamicTriggerPathList": [{"key": "onFilterUpdate"}],
    "labelPosition": "Top",
    "sourceData": "{{Select_labours1.data}}",
    "key": "2sdq33hmf7",
    "labelTextSize": "0.875rem",
    "isDeprecated": false,
    "rightColumn": 31,
    "thumbnailSVG": "https://appcdn.appsmith.com/static/media/thumbnail.9aef24cb159e9c6e4d0f1d7ca4fb0c79.svg",
    "widgetId": "y0jne42l59",
    "optionValue": "id",
    "minWidth": 450,
    "parentId": "t7iz5nzjyt",
    "labelAlignment": "left",
    "renderMode": "CANVAS",
    "mobileTopRow": 212,
    "optionLabel": "name",
    "responsiveBehavior": "fill",
    "originalTopRow": 197,
    "mobileLeftColumn": 0,
    "maxDynamicHeight": 9000,
    "onFilterUpdate": "{{\n            Select_labours1.run();\n            \n          }}",
    "minDynamicHeight": 4
}