{
  "gitSyncId": "665ff03890031b34850fab0e_f96643d2-dee0-40d6-9bd9-6b6c368ae278",
  "id": "Add Products_Dynamic_attribute.hideInput8",
  "pluginId": "js-plugin",
  "pluginType": "JS",
  "unpublishedAction": {
    "actionConfiguration": {
      "encodeParamsToggle": true,
      "jsArguments": [],
      "paginationType": "NONE",
      "timeoutInMillisecond": 10000
    },
    "collectionId": "Add Products_Dynamic_attribute",
    "confirmBeforeExecute": false,
    "datasource": {
      "isAutoGenerated": false,
      "name": "UNUSED_DATASOURCE",
      "pluginId": "js-plugin"
    },
    "dynamicBindingPathList": [
      {
        "key": "body"
      }
    ],
    "executeOnLoad": false,
    "fullyQualifiedName": "Dynamic_attribute.hideInput8",
    "name": "hideInput8",
    "pageId": "Add Products",
    "userSetOnLoad": false
  }
}